[{"__type__":"cc.SpriteFrame","content":{"name":"cover","texture":"1b194ad2a","rect":[3,1685,10,10],"offset":[0,0],"originalSize":[10,10],"capInsets":[2,2,2,2]}},{"__type__":"cc.SpriteFrame","content":{"name":"btn_backhome","texture":"1b194ad2a","rect":[993,3,297,138],"offset":[-1,0],"originalSize":[299,138],"rotated":1,"capInsets":[0,0,0,0]}},[{"__type__":"cc.Prefab","_name":"pause-box","data":{"__id__":1}},{"__type__":"cc.Node","_name":"pause-box","_children":[{"__id__":2}],"_level":1,"_components":[{"__type__":"cc.Sprite","node":{"__id__":1},"_spriteFrame":{"__uuid__":"2b0r1e3HRGK4r+6o06HVof"},"_sizeMode":0},{"__type__":"cc.Widget","node":{"__id__":1},"_alignFlags":45,"_originalWidth":10,"_originalHeight":10},{"__type__":"cc.Button","node":{"__id__":1},"clickEvents":[{"__type__":"cc.ClickEvent","target":{"__id__":1},"_componentId":"cc.Button"}]},{"__type__":"3c930MNghFAKLgFF/tPuxbg","node":{"__id__":1},"popBox":{"__id__":2}}],"_prefab":{"__type__":"cc.PrefabInfo","root":{"__id__":1},"asset":{"__uuid__":"87mIxC3FVHfbP0UligPqgu"},"fileId":"ddT1Zb1SVF4rZDK5eZpT8y"},"_contentSize":{"__type__":"cc.Size","width":750,"height":1334},"_position":{"__type__":"cc.Vec3","x":375,"y":667},"_scale":{"__type__":"cc.Vec3","x":1,"y":1,"z":1},"_zIndex":0},{"__type__":"cc.Node","_name":"content","_parent":{"__id__":1},"_children":[{"__id__":3},{"__id__":4},{"__id__":5}],"_level":2,"_prefab":{"__type__":"cc.PrefabInfo","root":{"__id__":1},"asset":{"__uuid__":"87mIxC3FVHfbP0UligPqgu"},"fileId":"6e8RBMYIRP5ouYA3smefCo"},"_contentSize":{"__type__":"cc.Size","width":500,"height":500},"_scale":{"__type__":"cc.Vec3","x":1,"y":1,"z":1},"_zIndex":0},{"__type__":"cc.Node","_name":"btn_again","_parent":{"__id__":2},"_level":3,"_components":[{"__type__":"cc.Sprite","node":{"__id__":3},"_spriteFrame":{"__uuid__":"89BKd1wT5Oj6VIoY0BDoNA"}},{"__type__":"cc.Button","node":{"__id__":3},"clickEvents":[{"__type__":"cc.ClickEvent","target":{"__id__":1},"_componentId":"3c930MNghFAKLgFF/tPuxbg","handler":"playAgain"}]},{"__type__":"ed97dNRAJhKsKj4mTJlxQ2l","node":{"__id__":3}}],"_prefab":{"__type__":"cc.PrefabInfo","root":{"__id__":1},"asset":{"__uuid__":"87mIxC3FVHfbP0UligPqgu"},"fileId":"78mi1mM9pF/or+p2JnIpw4"},"_contentSize":{"__type__":"cc.Size","width":297,"height":138},"_scale":{"__type__":"cc.Vec3","x":1,"y":1,"z":1},"_zIndex":0},{"__type__":"cc.Node","_name":"btn_backhome","_parent":{"__id__":2},"_level":3,"_components":[{"__type__":"cc.Sprite","node":{"__id__":4},"_spriteFrame":{"__uuid__":"58/Ly9STtAp78PIS4WSIXM"}},{"__type__":"cc.Button","node":{"__id__":4},"clickEvents":[{"__type__":"cc.ClickEvent","target":{"__id__":1},"_componentId":"3c930MNghFAKLgFF/tPuxbg","handler":"backHome"}]},{"__type__":"ed97dNRAJhKsKj4mTJlxQ2l","node":{"__id__":4}}],"_prefab":{"__type__":"cc.PrefabInfo","root":{"__id__":1},"asset":{"__uuid__":"87mIxC3FVHfbP0UligPqgu"},"fileId":"fc0IMZWgFAjY2cDKU/id77"},"_contentSize":{"__type__":"cc.Size","width":297,"height":138},"_position":{"__type__":"cc.Vec3","y":200},"_scale":{"__type__":"cc.Vec3","x":1,"y":1,"z":1},"_zIndex":0},{"__type__":"cc.Node","_name":"btn_next","_parent":{"__id__":2},"_level":3,"_components":[{"__type__":"cc.Sprite","node":{"__id__":5},"_spriteFrame":{"__uuid__":"c0LF+3+zhAlbUG0rhjkF3G"}},{"__type__":"cc.Button","node":{"__id__":5},"clickEvents":[{"__type__":"cc.ClickEvent","target":{"__id__":1},"_componentId":"3c930MNghFAKLgFF/tPuxbg","handler":"next"}]},{"__type__":"ed97dNRAJhKsKj4mTJlxQ2l","node":{"__id__":5}}],"_prefab":{"__type__":"cc.PrefabInfo","root":{"__id__":1},"asset":{"__uuid__":"87mIxC3FVHfbP0UligPqgu"},"fileId":"06lxe1GQ5EUb5QY5Ew7wFm"},"_contentSize":{"__type__":"cc.Size","width":311,"height":139},"_position":{"__type__":"cc.Vec3","x":9,"y":-200},"_scale":{"__type__":"cc.Vec3","x":1,"y":1,"z":1},"_zIndex":0}],{"__type__":"cc.SpriteFrame","content":{"name":"btn_again","texture":"1b194ad2a","rect":[1740,3,297,138],"offset":[-1,0],"originalSize":[299,138],"capInsets":[0,0,0,0]}},{"__type__":"cc.SpriteFrame","content":{"name":"btn_next","texture":"1b194ad2a","rect":[1252,3,311,139],"offset":[-1.5,0],"originalSize":[314,139],"rotated":1,"capInsets":[0,0,0,0]}}]